CREDITS.txt
ChangeLog
DEVELOPERS.txt
INSTALL.txt
LICENSE.txt
MANIFEST.in
README.txt
TODO.txt
bash_completion
ez_setup.py
setup.cfg
setup.py
src/instancemanager/__init__.py
src/instancemanager/actions.py
src/instancemanager/actionutils.py
src/instancemanager/changeownership.py
src/instancemanager/compat.py
src/instancemanager/config.py
src/instancemanager/configuration.py
src/instancemanager/copy_defaults_to_userdefaults.py
src/instancemanager/defaults.py
src/instancemanager/mainprogram.py
src/instancemanager/pack.py
src/instancemanager/quickreinstaller.py
src/instancemanager/sources.py
src/instancemanager/tests.py
src/instancemanager/uninstaller.py
src/instancemanager/utils.py
src/instancemanager/workingenv.py
src/instancemanager.egg-info/PKG-INFO
src/instancemanager.egg-info/SOURCES.txt
src/instancemanager.egg-info/dependency_links.txt
src/instancemanager.egg-info/entry_points.txt
src/instancemanager.egg-info/requires.txt
src/instancemanager.egg-info/top_level.txt
src/instancemanager/skeleton/README.txt
src/instancemanager/skeleton/__init__.py
src/instancemanager/skeleton/userdefaults.py
src_gui/imgui.py
