Metadata-Version: 1.0
Name: instancemanager
Version: 1.0
Summary: Manager for zope instances
Home-page: http://plone.org/products/instance-manager
Author: Reinout van Rees
Author-email: reinout@vanrees.org
License: GPL
Keywords: zope plone instances
Platform: UNKNOWN
